{"chunk":0,"numChunks":36,"fileHash":"5PxeaT4n9kgvALpAj5B1jgQlallPIdU12UlI5e4vOJw=","filePath":"src/services/finance_overview.js","content":"/**\n * Financial Planning Tools - Financial Overview Generator\n * \n * This module creates a comprehensive financial overview sheet based on transaction data.\n * It generates a complete overview with dynamic categories and optional sub-category display\n * based on user preference.\n * \n * Version: 2.1.0\n * Last Updated: 2025-05-08\n */\n/**\n * @namespace FinancialPlanner.FinanceOverview\n * @description Service responsible for generating a comprehensive financial overview sheet.\n */"}