{"chunk":10,"numChunks":25,"fileHash":"NFeCXCcs54GgVRSaoZ7YUMS8I/hASRpntpW0s0paeLI=","filePath":"src/tests/cache-service.test.js","content":"/**\n(function() {\n   const TestCacheService = (function(config) {\n       // --- Copy of CacheService Implementation Start ---\n        const memoryCache = {}; // Use a local var for the test instance's memory cache\n        function isCacheEnabled() {\n            // Use the provided mock config's current state\n            return config.getSection('CACHE').ENABLED === true;\n        }\n        function getDefaultExpirySeconds() {\n            return config.getSection('CACHE').EXPIRY_SECONDS || 3600;\n        }\n        function generateNamespacedKey(key) {\n            return `fp_${key}`;\n        }"}